{
  "id": "change.v.03",
  "definition": "become different in some particular way, without permanently losing one's or its former characteristics or essence",
  "depth": 0,
  "children": [
    {
      "id": "adapt.v.01",
      "definition": "make fit for, or change to suit a new purpose",
      "depth": 1,
      "children": [
        {
          "id": "adjust.v.04",
          "definition": "make correspondent or conformable",
          "depth": 2,
          "children": []
        },
        {
          "id": "anglicise.v.01",
          "definition": "make English in appearance",
          "depth": 2,
          "children": []
        },
        {
          "id": "christianize.v.01",
          "definition": "adapt in the name of Christianity",
          "depth": 2,
          "children": []
        },
        {
          "id": "domesticate.v.01",
          "definition": "adapt (a wild plant or unclaimed land) to the environment",
          "depth": 2,
          "children": []
        },
        {
          "id": "domesticate.v.03",
          "definition": "make fit for cultivation, domestic life, and service to humans",
          "depth": 2,
          "children": []
        },
        {
          "id": "electrify.v.03",
          "definition": "equip for use with electricity",
          "depth": 2,
          "children": []
        },
        {
          "id": "fit.v.05",
          "definition": "insert or adjust several objects or people",
          "depth": 2,
          "children": []
        },
        {
          "id": "gear.v.01",
          "definition": "set the level or character of",
          "depth": 2,
          "children": [
            {
              "id": "popularize.v.02",
              "definition": "make understandable to the general public",
              "depth": 3,
              "children": []
            }
          ]
        },
        {
          "id": "naturalize.v.03",
          "definition": "adopt to another place",
          "depth": 2,
          "children": []
        },
        {
          "id": "shoehorn.v.01",
          "definition": "fit for a specific purpose even when not well suited",
          "depth": 2,
          "children": []
        },
        {
          "id": "tailor.v.01",
          "definition": "adjust to a specific need or market",
          "depth": 2,
          "children": []
        },
        {
          "id": "transcribe.v.03",
          "definition": "rewrite or arrange a piece of music for an instrument or medium other than that originally intended",
          "depth": 2,
          "children": []
        }
      ]
    },
    {
      "id": "alternate.v.01",
      "definition": "go back and forth; swing back and forth between two states or conditions",
      "depth": 1,
      "children": []
    },
    {
      "id": "avianize.v.01",
      "definition": "to modify microorganisms by repeated culture in the developing chick embryo",
      "depth": 1,
      "children": []
    },
    {
      "id": "break.v.24",
      "definition": "vary or interrupt a uniformity or continuity",
      "depth": 1,
      "children": []
    },
    {
      "id": "crackle.v.03",
      "definition": "to become, or to cause to become, covered with a network of small cracks",
      "depth": 1,
      "children": []
    },
    {
      "id": "diversify.v.02",
      "definition": "spread into new habitats and produce variety or variegate",
      "depth": 1,
      "children": []
    },
    {
      "id": "diversify.v.03",
      "definition": "vary in order to spread risk or to expand",
      "depth": 1,
      "children": []
    },
    {
      "id": "honeycomb.v.03",
      "definition": "make full of cavities, like a honeycomb",
      "depth": 1,
      "children": []
    },
    {
      "id": "let_out.v.04",
      "definition": "make (clothes) larger",
      "depth": 1,
      "children": []
    },
    {
      "id": "modulate.v.05",
      "definition": "vary the frequency, amplitude, phase, or other characteristic of (electromagnetic waves)",
      "depth": 1,
      "children": []
    },
    {
      "id": "move.v.07",
      "definition": "go or proceed from one point to another",
      "depth": 1,
      "children": [
        {
          "id": "scroll.v.01",
          "definition": "move through text or graphics in order to display parts that do not fit on the screen",
          "depth": 2,
          "children": []
        },
        {
          "id": "sink.v.03",
          "definition": "pass into a specified state or condition",
          "depth": 2,
          "children": []
        },
        {
          "id": "step.v.10",
          "definition": "move or proceed as if by steps into a new situation",
          "depth": 2,
          "children": []
        }
      ]
    },
    {
      "id": "specialize.v.01",
      "definition": "become more focus on an area of activity or field of study",
      "depth": 1,
      "children": [
        {
          "id": "overspecialize.v.01",
          "definition": "become overly specialized",
          "depth": 2,
          "children": []
        }
      ]
    },
    {
      "id": "take_in.v.17",
      "definition": "make (clothes) smaller",
      "depth": 1,
      "children": []
    }
  ]
}