{
  "id": "disappear.v.01",
  "definition": "get lost, as without warning or explanation",
  "depth": 0,
  "children": [
    {
      "id": "absent.v.01",
      "definition": "go away or leave",
      "depth": 1,
      "children": []
    },
    {
      "id": "desorb.v.01",
      "definition": "go away from the surface to which (a substance) is adsorbed",
      "depth": 1,
      "children": []
    },
    {
      "id": "die.v.10",
      "definition": "disappear or come to an end",
      "depth": 1,
      "children": []
    },
    {
      "id": "die_out.v.01",
      "definition": "become extinct",
      "depth": 1,
      "children": []
    },
    {
      "id": "evanesce.v.01",
      "definition": "disappear gradually",
      "depth": 1,
      "children": []
    },
    {
      "id": "fade.v.02",
      "definition": "lose freshness, vigor, or vitality",
      "depth": 1,
      "children": []
    },
    {
      "id": "fall.v.31",
      "definition": "go as if by falling",
      "depth": 1,
      "children": []
    },
    {
      "id": "fall_off.v.03",
      "definition": "diminish in size or intensity",
      "depth": 1,
      "children": []
    },
    {
      "id": "go.v.09",
      "definition": "be abolished or discarded",
      "depth": 1,
      "children": []
    },
    {
      "id": "skip_town.v.01",
      "definition": "disappear without notifying anyone (idiom)",
      "depth": 1,
      "children": []
    }
  ]
}