{
  "id": "remember.v.01",
  "definition": "recall knowledge from memory; have a recollection",
  "depth": 0,
  "children": [
    {
      "id": "know.v.11",
      "definition": "perceive as familiar",
      "depth": 1,
      "children": []
    },
    {
      "id": "recognize.v.04",
      "definition": "perceive to be the same",
      "depth": 1,
      "children": [
        {
          "id": "identify.v.06",
          "definition": "consider to be equal or the same",
          "depth": 2,
          "children": [
            {
              "id": "mistake.v.01",
              "definition": "identify incorrectly",
              "depth": 3,
              "children": [
                {
                  "id": "confuse.v.01",
                  "definition": "mistake one thing for another",
                  "depth": 4,
                  "children": []
                }
              ]
            },
            {
              "id": "taste.v.05",
              "definition": "distinguish flavors",
              "depth": 3,
              "children": []
            },
            {
              "id": "type.v.02",
              "definition": "identify as belonging to a certain type",
              "depth": 3,
              "children": []
            }
          ]
        }
      ]
    },
    {
      "id": "review.v.04",
      "definition": "refresh one's memory",
      "depth": 1,
      "children": []
    }
  ]
}